Skolmaten/__init__.py
Skolmaten/constants.py
Skolmaten/helpers.py
Skolmaten/skolmaten.py
Skolmaten-0.0.6.dist-info/LICENSE
Skolmaten-0.0.6.dist-info/METADATA
Skolmaten-0.0.6.dist-info/WHEEL
Skolmaten-0.0.6.dist-info/top_level.txt
Skolmaten-0.0.6.dist-info/RECORD
