Metadata-Version: 2.1
Name: Skolmaten
Version: 0.0.6
Summary: Fetch food menu information from skolmaten.se
Home-page: https://github.com/dunderrrrrr/skolmaten/
Author: dunderrrrrr
License-File: LICENSE
Requires-Dist: feedparser ==6.0.10
